README.md
setup.py
bankaya_data_utilities.egg-info/PKG-INFO
bankaya_data_utilities.egg-info/SOURCES.txt
bankaya_data_utilities.egg-info/dependency_links.txt
bankaya_data_utilities.egg-info/not-zip-safe
bankaya_data_utilities.egg-info/top_level.txt
data/__init__.py
data/cdc_parser.py
data/cdc_rules.py
data/dynamo.py
data/mysql.py
data/snowflake.py
data/util.py