Metadata-Version: 1.0
Name: bankaya-data-utilities
Version: 1.0.22
Summary: Driver for data access utilities
Home-page: https://bitbucket.org/bankaya-dev/data-utilities
Author: Enrique Garcia
Author-email: enrique@bankaya.com.mx
License: Bankaya
Platform: UNKNOWN
